MANIFEST.in
setup.cfg
setup.py
config/VERSION
config/requirements.txt
twentyc.database.egg-info/PKG-INFO
twentyc.database.egg-info/SOURCES.txt
twentyc.database.egg-info/dependency_links.txt
twentyc.database.egg-info/namespace_packages.txt
twentyc.database.egg-info/not-zip-safe
twentyc.database.egg-info/requires.txt
twentyc.database.egg-info/top_level.txt
twentyc/database/__init__.py
twentyc/database/base.py
twentyc/database/tools.py
twentyc/database/couchbase/__init__.py
twentyc/database/couchbase/client.py
twentyc/database/couchdb/__init__.py
twentyc/database/couchdb/client.py
twentyc/database/dummydb/__init__.py
twentyc/database/dummydb/client.py