Metadata-Version: 1.1
Name: twentyc.database
Version: 0.1.4
Summary: database abstractions
Home-page: https://github.com/20c/twentyc.database
Author: Twentieth Century
Author-email: code@20c.com
License: UNKNOWN
Download-URL: https://github.com/20c/twentyc.database/tarball/0.1.4
Platform: UNKNOWN
Classifier: Development Status :: 4 - Beta
Classifier: Intended Audience :: Developers
Classifier: License :: OSI Approved :: Apache Software License
Classifier: Topic :: Software Development :: Libraries :: Python Modules
